odoo10_addon_product_analytic-10.0.1.0.0-py2.7-nspkg.pth
odoo/addons/product_analytic/README.rst
odoo/addons/product_analytic/__init__.py
odoo/addons/product_analytic/__manifest__.py
odoo/addons/product_analytic/i18n/ca.po
odoo/addons/product_analytic/i18n/de.po
odoo/addons/product_analytic/i18n/es.po
odoo/addons/product_analytic/i18n/es_MX.po
odoo/addons/product_analytic/i18n/fi.po
odoo/addons/product_analytic/i18n/fr.po
odoo/addons/product_analytic/i18n/fr_CH.po
odoo/addons/product_analytic/i18n/hr.po
odoo/addons/product_analytic/i18n/it.po
odoo/addons/product_analytic/i18n/nl.po
odoo/addons/product_analytic/i18n/pt_BR.po
odoo/addons/product_analytic/i18n/pt_PT.po
odoo/addons/product_analytic/i18n/sl.po
odoo/addons/product_analytic/i18n/tr.po
odoo/addons/product_analytic/i18n/tr_TR.po
odoo/addons/product_analytic/models/__init__.py
odoo/addons/product_analytic/models/account_invoice.py
odoo/addons/product_analytic/models/product.py
odoo/addons/product_analytic/tests/__init__.py
odoo/addons/product_analytic/tests/test_account_invoice.py
odoo/addons/product_analytic/views/product_view.xml
odoo10_addon_product_analytic-10.0.1.0.0.dist-info/DESCRIPTION.rst
odoo10_addon_product_analytic-10.0.1.0.0.dist-info/METADATA
odoo10_addon_product_analytic-10.0.1.0.0.dist-info/RECORD
odoo10_addon_product_analytic-10.0.1.0.0.dist-info/WHEEL
odoo10_addon_product_analytic-10.0.1.0.0.dist-info/metadata.json
odoo10_addon_product_analytic-10.0.1.0.0.dist-info/namespace_packages.txt
odoo10_addon_product_analytic-10.0.1.0.0.dist-info/top_level.txt
